<?xml version="1.0"?>
<psalm
    errorLevel="3"
    resolveFromConfigFile="true"
    xmlns:xsi="http://www.w3.org/2001/XMLSchema-instance"
    xmlns="https://getpsalm.org/schema/config"
    xsi:schemaLocation="https://getpsalm.org/schema/config vendor/vimeo/psalm/config.xsd"
>
    <projectFiles>
        <directory name="src"/>
        <directory name="public"/>
        <directory name="config"/>
        <ignoreFiles>
            <directory name="migrations"/>
            <directory name="vendor"/>
            <directory name="var"/>
            <file name="config/preload.php"/>
            <directory name="src/Repository"/>

        </ignoreFiles>
    </projectFiles>

    <issueHandlers>
        <PropertyNotSetInConstructor>
            <errorLevel type="suppress">
                <referencedProperty name="Symfony\Bundle\FrameworkBundle\Controller\AbstractController::$container"/>
            </errorLevel>
        </PropertyNotSetInConstructor>
    </issueHandlers>
</psalm>
